Metadata-Version: 2.1
Name: drf-flex-fields
Version: 0.8.1
Summary: Flexible, dynamic fields and nested resources for Django REST Framework serializers.
Home-page: https://github.com/rsinger86/drf-flex-fields
Author: Robert Singer
Author-email: robertgsinger@gmail.com
License: MIT
Keywords: django rest api dynamic fields
Platform: UNKNOWN
Classifier: License :: OSI Approved :: MIT License
Classifier: Programming Language :: Python :: 2.7
Classifier: Programming Language :: Python :: 3
Classifier: Programming Language :: Python :: 3.2
Classifier: Programming Language :: Python :: 3.3
Classifier: Programming Language :: Python :: 3.4
Classifier: Programming Language :: Python :: 3.5
Classifier: Programming Language :: Python :: 3.6
Classifier: Programming Language :: Python :: 3.7
